Workbook

Sheet Approved_KRIS
A1: APPROVED by KRIS
A3: Item | B3: Cost (Rs) | C3: Notes
A4: Creative Direction
A5: Creative Direction & Event Concept | B5: =Revenue!I2 -> 300000
A6: Design
A7: Logo Design | B7: =Revenue!I3 -> 90000
A8: Derivatives- Flyer/Pattern/BG | B8: =Revenue!I4 -> 70000
A9: Stage & Content
A10: CEO Keynote Presentation Design (incl. 100+ slides, graphics, storytelling) | B10: =Revenue!I5 -> 275000
A11: Speaker Presentations (x3) | B11: =Revenue!I6 -> 90000
A12: Screen / LED Content Management | B12: =Revenue!I7 -> 70000
A13: Sustenance
A14: Sustenance- Food, Drink, Fuel | B14: =Revenue!I8 -> 120000
A15: Visual Team (Talent Overseas) WOW Effect
A16: Backdrop Animation | B16: =Revenue!I9 -> 100000
A17: Walk-in & Ambience Music | B17: =Revenue!I10 -> 100000
A18: Content Capture
A19: Video Coverage (2-cam setup + edits) + BTS + Same day Edit | B19: =Revenue!I11 -> 220000
A20: Photography | B20: 100000
A21: Management & Coordination
A22: Santral Art/Nico | C22: TBC / not priced
A24: Summary
A25: Subtotal | B25: =SUM(B5:B20) -> 1535000
A26: DISCOUNT | B26: 80000
A27: Subtotal - Discount | B27: =B25-B26 -> 1455000
A28: Agency Fee (10%) | B28: =B27*0.1 -> 145500
A29: Subtotal + Agency | B29: =B28+B27 -> 1600500
A30: VAT (15%) | B30: =B29*0.15 -> 240075
A31: TOTAL ESTIMATE | B31: =B30+B29 -> 1840575

Sheet Lists
A1: Categories | C1: Expense Types | E1: Paid By | G1: Invoice Status | I1: Cash Status
A2: Creative Direction | C2: Freelance | E2: ë | G2: Draft | I2: Owed
A3: Design | C3: Supplier | E3: Avneesh | G3: Invoiced | I3: Reimbursed
A4: Video | C4: Cash | E4: Long | G4: Part-paid | I4: Settled/Net-off
A5: Tech/AV | C5: Card | E5: Williams | G5: Paid
A6: Scenography | C6: Bank Transfer | E6: Laura
A7: Sound Design | C7: Internal Allocation | E7: Other
A8: Travel | C8: Other | E8: Harsh
A9: Food | E9: Kunal
A10: Transport | E10: Petty Cash
A11: Accommodation
A12: Printing
A13: Rentals
A14: Marketing/PR
A15: Admin
A16: Other
A17: Production
A18: Photography

Sheet Revenue
A1: Date Approved | B1: Project | C1: Client | D1: Item Code | E1: Item Description | F1: Category | G1: Qty | H1: Unit Price (Rs) | I1: Line Total (Rs) | J1: Approved By | K1: Invoice Status | L1: Invoice # | M1: Paid Date | N1: Notes
B2: Mauritius Telecom Connect | C2: Mauritius Telecom | D2: MT-CON-01 | E2: Creative Direction & Event Concept | F2: Creative Direction | G2: 1 | H2: 300000 | I2: =IF(OR(G2="",H2=""),"",G2*H2) -> 300000 | J2: KRIS | K2: Draft
B3: Mauritius Telecom Connect | C3: Mauritius Telecom | D3: MT-CON-02 | E3: Logo Design | F3: Design | G3: 1 | H3: 90000 | I3: =IF(OR(G3="",H3=""),"",G3*H3) -> 90000 | J3: KRIS | K3: Draft
B4: Mauritius Telecom Connect | C4: Mauritius Telecom | D4: MT-CON-03 | E4: Derivatives- Flyer/Pattern/BG | F4: Design | G4: 1 | H4: 70000 | I4: =IF(OR(G4="",H4=""),"",G4*H4) -> 70000 | J4: KRIS | K4: Draft
B5: Mauritius Telecom Connect | C5: Mauritius Telecom | D5: MT-CON-04 | E5: CEO Keynote Presentation Design (incl. 100+ slides, graphics, storytelling) | F5: Design | G5: 1 | H5: 275000 | I5: =IF(OR(G5="",H5=""),"",G5*H5) -> 275000 | J5: KRIS | K5: Draft
B6: Mauritius Telecom Connect | C6: Mauritius Telecom | D6: MT-CON-05 | E6: Speaker Presentations (x3) | F6: Design | G6: 1 | H6: 90000 | I6: =IF(OR(G6="",H6=""),"",G6*H6) -> 90000 | J6: KRIS | K6: Draft
B7: Mauritius Telecom Connect | C7: Mauritius Telecom | D7: MT-CON-06 | E7: Screen / LED Content Management | F7: Tech/AV | G7: 1 | H7: 70000 | I7: =IF(OR(G7="",H7=""),"",G7*H7) -> 70000 | J7: KRIS | K7: Draft
B8: Mauritius Telecom Connect | C8: Mauritius Telecom | D8: MT-CON-07 | E8: Sustenance- Food, Drink, Fuel | F8: Food | G8: 1 | H8: 120000 | I8: =IF(OR(G8="",H8=""),"",G8*H8) -> 120000 | J8: KRIS | K8: Draft
B9: Mauritius Telecom Connect | C9: Mauritius Telecom | D9: MT-CON-08 | E9: Backdrop Animation | F9: Video | G9: 1 | H9: 100000 | I9: =IF(OR(G9="",H9=""),"",G9*H9) -> 100000 | J9: KRIS | K9: Draft
B10: Mauritius Telecom Connect | C10: Mauritius Telecom | D10: MT-CON-09 | E10: Walk-in & Ambience Music | F10: Production | G10: 1 | H10: 100000 | I10: =IF(OR(G10="",H10=""),"",G10*H10) -> 100000 | J10: KRIS | K10: Draft
B11: Mauritius Telecom Connect | C11: Mauritius Telecom | D11: MT-CON-10 | E11: Video Coverage (2-cam setup + edits) + BTS + Same day Edit | F11: Video | G11: 1 | H11: 220000 | I11: =IF(OR(G11="",H11=""),"",G11*H11) -> 220000 | J11: KRIS | K11: Draft
B12: Mauritius Telecom Connect | C12: Mauritius Telecom | D12: MT-CON-11 | E12: Photography | F12: Photography | G12: 1 | H12: 100000 | I12: =IF(OR(G12="",H12=""),"",G12*H12) -> 100000 | J12: KRIS | K12: Draft
G13: 1 | I13: =IF(OR(G13="",H13=""),"",G13*H13)
A14: TOTAL | G14: 1 | I14: =IF(OR(G14="",H14=""),"",G14*H14)
G15: 1 | I15: =IF(OR(G15="",H15=""),"",G15*H15)
G16: 1 | I16: =IF(OR(G16="",H16=""),"",G16*H16)
G17: 1 | I17: =IF(OR(G17="",H17=""),"",G17*H17)
G18: 1 | I18: =IF(OR(G18="",H18=""),"",G18*H18)
G19: 1 | I19: =IF(OR(G19="",H19=""),"",G19*H19)
G20: 1 | I20: =IF(OR(G20="",H20=""),"",G20*H20)
G21: 1 | I21: =IF(OR(G21="",H21=""),"",G21*H21)
G22: 1 | I22: =IF(OR(G22="",H22=""),"",G22*H22)
G23: 1 | I23: =IF(OR(G23="",H23=""),"",G23*H23)
G24: 1 | I24: =IF(OR(G24="",H24=""),"",G24*H24)
G25: 1 | I25: =IF(OR(G25="",H25=""),"",G25*H25)
G26: 1 | I26: =IF(OR(G26="",H26=""),"",G26*H26)
... G32: 1 | I32: =IF(OR(G32="",H32=""),"",G32*H32)

Sheet Expenses
A1: Date | B1: Project | C1: Description | D1: Category | E1: Supplier/Person | F1: Expense Type | G1: Amount (Rs) | H1: Paid By | I1: VAT Applicable | J1: VAT Rate | K1: VAT Amount (Rs) | L1: Total excl VAT (Rs) | M1: Receipt (Y/N) | N1: Accounting Status | O1: Reference/Receipt # | P1: Notes
B2: Mauritius Telecom Connect | C2: Video | D2: Video | E2: Neil VIDEO | F2: Freelance | G2: 205000 | H2: ë | I2: No | K2: =IF(OR(G2="",I2=""),"",IF(UPPER(I2)="YES",G2*J2,0)) -> 0 | L2: =IF(G2="","",G2+K2) -> 205000 | N2: Pending
B3: Mauritius Telecom Connect | C3: Creative Direction | D3: Creative Direction | E3: David | F3: Internal Allocation | G3: 50000 | H3: ë | I3: No | K3: =IF(OR(G3="",I3=""),"",IF(UPPER(I3)="YES",G3*J3,0)) -> 0 | L3: =IF(G3="","",G3+K3) -> 50000 | N3: Pending
B4: Mauritius Telecom Connect | C4: Creative Direction | D4: Creative Direction | E4: Kunal | F4: Internal Allocation | G4: 119000 | H4: ë | I4: No | K4: =IF(OR(G4="",I4=""),"",IF(UPPER(I4)="YES",G4*J4,0)) -> 0 | L4: =IF(G4="","",G4+K4) -> 119000 | N4: Pending
B5: Mauritius Telecom Connect | C5: Design | D5: Design | E5: Harsh | F5: Freelance | G5: 120000 | H5: ë | I5: No | K5: =IF(OR(G5="",I5=""),"",IF(UPPER(I5)="YES",G5*J5,0)) -> 0 | L5: =IF(G5="","",G5+K5) -> 120000 | N5: Pending
B6: Mauritius Telecom Connect | C6: Video | D6: Video | E6: Dopeman | F6: Freelance | G6: 50000 | H6: ë | I6: No | K6: =IF(OR(G6="",I6=""),"",IF(UPPER(I6)="YES",G6*J6,0)) -> 0 | L6: =IF(G6="","",G6+K6) -> 50000 | N6: Pending
B7: Mauritius Telecom Connect | C7: Other | D7: Other | E7: Others | F7: Supplier | G7: 24500 | H7: ë | I7: No | K7: =IF(OR(G7="",I7=""),"",IF(UPPER(I7)="YES",G7*J7,0)) -> 0 | L7: =IF(G7="","",G7+K7) -> 24500 | N7: Pending
B8: Mauritius Telecom Connect | C8: Creative Direction | D8: Creative Direction | E8: Avneesh | F8: Internal Allocation | G8: 180000 | H8: ë | I8: No | K8: =IF(OR(G8="",I8=""),"",IF(UPPER(I8)="YES",G8*J8,0)) -> 0 | L8: =IF(G8="","",G8+K8) -> 180000 | N8: Pending
B9: Mauritius Telecom Connect | C9: Production | D9: Production | E9: Kevin | F9: Freelance | G9: 70000 | H9: ë | I9: No | K9: =IF(OR(G9="",I9=""),"",IF(UPPER(I9)="YES",G9*J9,0)) -> 0 | L9: =IF(G9="","",G9+K9) -> 70000 | N9: Pending
B10: Mauritius Telecom Connect | C10: Video | D10: Video | E10: Lakshraj – Video Trade Route | F10: Freelance | G10: 10000 | H10: ë | I10: No | K10: =IF(OR(G10="",I10=""),"",IF(UPPER(I10)="YES",G10*J10,0)) -> 0 | L10: =IF(G10="","",G10+K10) -> 10000 | N10: Pending
B11: Mauritius Telecom Connect | C11: Video | D11: Video | E11: Gloria | F11: Freelance | G11: 20000 | H11: ë | I11: No | K11: =IF(OR(G11="",I11=""),"",IF(UPPER(I11)="YES",G11*J11,0)) -> 0 | L11: =IF(G11="","",G11+K11) -> 20000 | N11: Pending
B12: Mauritius Telecom Connect | C12: Admin | D12: Admin | E12: Store | F12: Supplier | G12: 25000 | H12: ë | I12: No | K12: =IF(OR(G12="",I12=""),"",IF(UPPER(I12)="YES",G12*J12,0)) -> 0 | L12: =IF(G12="","",G12+K12) -> 25000 | N12: Pending
A13: 45977 | B13: Mauritius Telecom Connect | C13: Pizza + Menwar team at studio | D13: Food | E13: Petty Cash | F13: Cash | G13: 385 | H13: Petty Cash | I13: Yes | J13: 0.15 | K13: =IF(OR(G13="",I13=""),"",IF(UPPER(I13)="YES",G13*J13,0)) -> 57.75 | L13: =IF(G13="","",G13-K13) -> 327.25 | N13: Pending | P13: Source: Petty Cash OUT list
A14: 45977 | B14: Mauritius Telecom Connect | C14: Millions Burger | D14: Food | E14: Petty Cash | F14: Cash | G14: 7000 | H14: Petty Cash | I14: Yes | J14: 0.15 | K14: =IF(OR(G14="",I14=""),"",IF(UPPER(I14)="YES",G14*J14,0)) -> 1050 | L14: =IF(G14="","",G14-K14) -> 5950 | N14: Pending | P14: Source: Petty Cash OUT list
A15: 45977 | B15: Mauritius Telecom Connect | C15: Others | D15: Other | E15: Petty Cash | F15: Cash | G15: 750 | H15: Petty Cash | I15: No | K15: =IF(OR(G15="",I15=""),"",IF(UPPER(I15)="YES",G15*J15,0)) -> 0 | L15: =IF(G15="","",G15+K15) -> 750 | N15: Pending | P15: Source: Petty Cash OUT list
A16: 45978 | B16: Mauritius Telecom Connect | C16: Millions Burger | D16: Food | E16: Petty Cash | F16: Cash | G16: 1446 | H16: Petty Cash | I16: Yes | J16: 0.15 | K16: =IF(OR(G16="",I16=""),"",IF(UPPER(I16)="YES",G16*J16,0)) -> 216.9 | L16: =IF(G16="","",G16-K16) -> 1229.1 | N16: Pending | P16: Source: Petty Cash OUT list
A17: 45985 | B17: Mauritius Telecom Connect | C17: Food | D17: Food | E17: Petty Cash | F17: Cash | G17: 3500 | H17: Petty Cash | I17: Yes | J17: 0.15 | K17: =IF(OR(G17="",I17=""),"",IF(UPPER(I17)="YES",G17*J17,0)) -> 525 | L17: =IF(G17="","",G17-K17) -> 2975 | N17: Pending | P17: Source: Petty Cash OUT list
A18: 45986 | B18: Mauritius Telecom Connect | C18: Gato | D18: Food | E18: Petty Cash | F18: Cash | G18: 500 | H18: Petty Cash | I18: Yes | J18: 0.15 | K18: =IF(OR(G18="",I18=""),"",IF(UPPER(I18)="YES",G18*J18,0)) -> 75 | L18: =IF(G18="","",G18-K18) -> 425 | N18: Pending | P18: Source: Petty Cash OUT list
A19: 45986 | B19: Mauritius Telecom Connect | C19: Carnet | D19: Other | E19: Petty Cash | F19: Cash | G19: 400 | H19: Petty Cash | I19: No | K19: =IF(OR(G19="",I19=""),"",IF(UPPER(I19)="YES",G19*J19,0)) -> 0 | L19: =IF(G19="","",G19+K19) -> 400 | N19: Pending | P19: Source: Petty Cash OUT list
A20: 45986 | B20: Mauritius Telecom Connect | C20: Harsh | D20: Other | E20: Petty Cash | F20: Cash | G20: 2960.5 | H20: Petty Cash | I20: No | K20: =IF(OR(G20="",I20=""),"",IF(UPPER(I20)="YES",G20*J20,0)) -> 0 | L20: =IF(G20="","",G20+K20) -> 2960.5 | N20: Pending | P20: Source: Petty Cash OUT list
A21: 45986 | B21: Mauritius Telecom Connect | C21: Food | D21: Food | E21: Petty Cash | F21: Cash | G21: 170 | H21: Petty Cash | I21: Yes | J21: 0.15 | K21: =IF(OR(G21="",I21=""),"",IF(UPPER(I21)="YES",G21*J21,0)) -> 25.5 | L21: =IF(G21="","",G21-K21) -> 144.5 | N21: Pending | P21: Source: Petty Cash OUT list
A22: 45987 | B22: Mauritius Telecom Connect | C22: Food | D22: Food | E22: Petty Cash | F22: Cash | G22: 1446 | H22: Petty Cash | I22: Yes | J22: 0.15 | K22: =IF(OR(G22="",I22=""),"",IF(UPPER(I22)="YES",G22*J22,0)) -> 216.9 | L22: =IF(G22="","",G22-K22) -> 1229.1 | N22: Pending | P22: Source: Petty Cash OUT list
A23: 45987 | B23: Mauritius Telecom Connect | C23: refund harsh food | D23: Food | E23: Petty Cash | F23: Cash | G23: 2755 | H23: Petty Cash | I23: Yes | J23: 0.15 | K23: =IF(OR(G23="",I23=""),"",IF(UPPER(I23)="YES",G23*J23,0)) -> 413.25 | L23: =IF(G23="","",G23-K23) -> 2341.75 | N23: Pending | P23: Source: Petty Cash OUT list
A24: 45987 | B24: Mauritius Telecom Connect | C24: Food | D24: Food | E24: Petty Cash | F24: Cash | G24: 485 | H24: Petty Cash | I24: Yes | J24: 0.15 | K24: =IF(OR(G24="",I24=""),"",IF(UPPER(I24)="YES",G24*J24,0)) -> 72.75 | L24: =IF(G24="","",G24-K24) -> 412.25 | N24: Pending | P24: Source: Petty Cash OUT list
A25: 45988 | B25: Mauritius Telecom Connect | C25: Other | D25: Other | E25: Petty Cash | F25: Cash | G25: 4000 | H25: Petty Cash | I25: No | K25: =IF(OR(G25="",I25=""),"",IF(UPPER(I25)="YES",G25*J25,0)) -> 0 | L25: =IF(G25="","",G25+K25) -> 4000 | N25: Pending | P25: Source: Petty Cash OUT list
A26: 45988 | B26: Mauritius Telecom Connect | C26: Other | D26: Other | E26: Petty Cash | F26: Cash | G26: 411 | H26: Petty Cash | I26: No | K26: =IF(OR(G26="",I26=""),"",IF(UPPER(I26)="YES",G26*J26,0)) -> 0 | L26: =IF(G26="","",G26+K26) -> 411 | N26: Pending | P26: Source: Petty Cash OUT list
A27: 45988 | B27: Mauritius Telecom Connect | C27: Food | D27: Food | E27: Petty Cash | F27: Cash | G27: 460 | H27: Petty Cash | I27: Yes | J27: 0.15 | K27: =IF(OR(G27="",I27=""),"",IF(UPPER(I27)="YES",G27*J27,0)) -> 69 | L27: =IF(G27="","",G27-K27) -> 391 | N27: Pending | P27: Source: Petty Cash OUT list
A28: 45988 | B28: Mauritius Telecom Connect | C28: Others | D28: Other | E28: Petty Cash | F28: Cash | G28: 2070 | H28: Petty Cash | I28: No | K28: =IF(OR(G28="",I28=""),"",IF(UPPER(I28)="YES",G28*J28,0)) -> 0 | L28: =IF(G28="","",G28+K28) -> 2070 | N28: Pending | P28: Source: Petty Cash OUT list
A29: 45988 | B29: Mauritius Telecom Connect | C29: Groceries | D29: Food | E29: Petty Cash | F29: Cash | G29: 2900 | H29: Petty Cash | I29: Yes | J29: 0.15 | K29: =IF(OR(G29="",I29=""),"",IF(UPPER(I29)="YES",G29*J29,0)) -> 435 | L29: =IF(G29="","",G29-K29) -> 2465 | N29: Pending | P29: Source: Petty Cash OUT list
A30: 45988 | B30: Mauritius Telecom Connect | C30: Food | D30: Food | E30: Petty Cash | F30: Cash | G30: 477 | H30: Petty Cash | I30: Yes | J30: 0.15 | K30: =IF(OR(G30="",I30=""),"",IF(UPPER(I30)="YES",G30*J30,0)) -> 71.55 | L30: =IF(G30="","",G30-K30) -> 405.45 | N30: Pending | P30: Source: Petty Cash OUT list
A31: 45989 | B31: Mauritius Telecom Connect | C31: Food | D31: Food | E31: Petty Cash | F31: Cash | G31: 1800 | H31: Petty Cash | I31: Yes | J31: 0.15 | K31: =IF(OR(G31="",I31=""),"",IF(UPPER(I31)="YES",G31*J31,0)) -> 270 | L31: =IF(G31="","",G31-K31) -> 1530 | N31: Pending | P31: Source: Petty Cash OUT list
A32: 45989 | B32: Mauritius Telecom Connect | C32: AI BANANA | D32: Other | E32: Petty Cash | F32: Cash | G32: 3095 | H32: Petty Cash | I32: No | K32: =IF(OR(G32="",I32=""),"",IF(UPPER(I32)="YES",G32*J32,0)) -> 0 | L32: =IF(G32="","",G32+K32) -> 3095 | N32: Pending | P32: Source: Petty Cash OUT list
A33: 45989 | B33: Mauritius Telecom Connect | C33: Food | D33: Food | E33: Petty Cash | F33: Cash | G33: 940 | H33: Petty Cash | I33: Yes | J33: 0.15 | K33: =IF(OR(G33="",I33=""),"",IF(UPPER(I33)="YES",G33*J33,0)) -> 141 | L33: =IF(G33="","",G33-K33) -> 799 | N33: Pending | P33: Source: Petty Cash OUT list
A34: 45990 | B34: Mauritius Telecom Connect | C34: Food | D34: Food | E34: Petty Cash | F34: Cash | G34: 1590 | H34: Petty Cash | I34: Yes | J34: 0.15 | K34: =IF(OR(G34="",I34=""),"",IF(UPPER(I34)="YES",G34*J34,0)) -> 238.5 | L34: =IF(G34="","",G34-K34) -> 1351.5 | N34: Pending | P34: Source: Petty Cash OUT list
A35: 45991 | B35: Mauritius Telecom Connect | C35: Food | D35: Food | E35: Petty Cash | F35: Cash | G35: 440 | H35: Petty Cash | I35: Yes | J35: 0.15 | K35: =IF(OR(G35="",I35=""),"",IF(UPPER(I35)="YES",G35*J35,0)) -> 66 | L35: =IF(G35="","",G35-K35) -> 374 | N35: Pending | P35: Source: Petty Cash OUT list
A36: 45991 | B36: Mauritius Telecom Connect | C36: other | D36: Other | E36: Petty Cash | F36: Cash | G36: 145 | H36: Petty Cash | I36: No | K36: =IF(OR(G36="",I36=""),"",IF(UPPER(I36)="YES",G36*J36,0)) -> 0 | L36: =IF(G36="","",G36+K36) -> 145 | N36: Pending | P36: Source: Petty Cash OUT list
A37: 45991 | B37: Mauritius Telecom Connect | C37: Food | D37: Food | E37: Petty Cash | F37: Cash | G37: 2500 | H37: Petty Cash | I37: Yes | J37: 0.15 | K37: =IF(OR(G37="",I37=""),"",IF(UPPER(I37)="YES",G37*J37,0)) -> 375 | L37: =IF(G37="","",G37-K37) -> 2125 | N37: Pending | P37: Source: Petty Cash OUT list
A38: 45992 | B38: Mauritius Telecom Connect | C38: Drink | D38: Food | E38: Petty Cash | F38: Cash | G38: 1000 | H38: Petty Cash | I38: Yes | J38: 0.15 | K38: =IF(OR(G38="",I38=""),"",IF(UPPER(I38)="YES",G38*J38,0)) -> 150 | L38: =IF(G38="","",G38-K38) -> 850 | N38: Pending | P38: Source: Petty Cash OUT list
A39: 45992 | B39: Mauritius Telecom Connect | C39: Food Eric | D39: Food | E39: Petty Cash | F39: Cash | G39: 440 | H39: Petty Cash | I39: Yes | J39: 0.15 | K39: =IF(OR(G39="",I39=""),"",IF(UPPER(I39)="YES",G39*J39,0)) -> 66 | L39: =IF(G39="","",G39-K39) -> 374 | N39: Pending | P39: Source: Petty Cash OUT list
A40: 45993 | B40: Mauritius Telecom Connect | C40: other | D40: Other | E40: Petty Cash | F40: Cash | G40: 2775 | H40: Petty Cash | I40: No | K40: =IF(OR(G40="",I40=""),"",IF(UPPER(I40)="YES",G40*J40,0)) -> 0 | L40: =IF(G40="","",G40+K40) -> 2775 | N40: Pending | P40: Source: Petty Cash OUT list
A41: 45993 | B41: Mauritius Telecom Connect | C41: Food | D41: Food | E41: Petty Cash | F41: Cash | G41: 7000 | H41: Petty Cash | I41: Yes | J41: 0.15 | K41: =IF(OR(G41="",I41=""),"",IF(UPPER(I41)="YES",G41*J41,0)) -> 1050 | L41: =IF(G41="","",G41-K41) -> 5950 | N41: Pending | P41: Source: Petty Cash OUT list
A42: 45993 | B42: Mauritius Telecom Connect | C42: Others | D42: Other | E42: Petty Cash | F42: Cash | G42: 818 | H42: Petty Cash | I42: No | K42: =IF(OR(G42="",I42=""),"",IF(UPPER(I42)="YES",G42*J42,0)) -> 0 | L42: =IF(G42="","",G42+K42) -> 818 | N42: Pending | P42: Source: Petty Cash OUT list
A43: 45993 | B43: Mauritius Telecom Connect | C43: Food | D43: Food | E43: Petty Cash | F43: Cash | G43: 122.74 | H43: Petty Cash | I43: Yes | J43: 0.15 | K43: =IF(OR(G43="",I43=""),"",IF(UPPER(I43)="YES",G43*J43,0)) -> 18.411 | L43: =IF(G43="","",G43-K43) -> 104.329 | N43: Pending | P43: Source: Petty Cash OUT list
A44: 45994 | B44: Mauritius Telecom Connect | C44: Food | D44: Food | E44: Petty Cash | F44: Cash | G44: 2850 | H44: Petty Cash | I44: Yes | J44: 0.15 | K44: =IF(OR(G44="",I44=""),"",IF(UPPER(I44)="YES",G44*J44,0)) -> 427.5 | L44: =IF(G44="","",G44-K44) -> 2422.5 | N44: Pending | P44: Source: Petty Cash OUT list
A45: 45994 | B45: Mauritius Telecom Connect | C45: Pendrive | D45: Tech/AV | E45: Petty Cash | F45: Cash | G45: 810 | H45: Petty Cash | I45: No | K45: =IF(OR(G45="",I45=""),"",IF(UPPER(I45)="YES",G45*J45,0)) -> 0 | L45: =IF(G45="","",G45+K45) -> 810 | N45: Pending | P45: Source: Petty Cash OUT list
A46: 45996 | B46: Mauritius Telecom Connect | C46: (unspecified) | D46: Other | E46: Petty Cash | F46: Cash | G46: 942.21 | H46: Petty Cash | I46: No | K46: =IF(OR(G46="",I46=""),"",IF(UPPER(I46)="YES",G46*J46,0)) -> 0 | L46: =IF(G46="","",G46+K46) -> 942.21 | N46: Pending | P46: Source: Petty Cash OUT list
A47: 45969 | B47: Mauritius Telecom Connect | C47: Fuel | D47: Transport | E47: Harsh | F47: Cash | G47: 600 | H47: Harsh | I47: No | K47: =IF(OR(G47="",I47=""),"",IF(UPPER(I47)="YES",G47*J47,0)) -> 0 | L47: =IF(G47="","",G47+K47) -> 600 | N47: Pending | P47: Source: Harsh fuel list
A48: 45973 | B48: Mauritius Telecom Connect | C48: Fuel | D48: Transport | E48: Harsh | F48: Cash | G48: 600 | H48: Harsh | I48: No | K48: =IF(OR(G48="",I48=""),"",IF(UPPER(I48)="YES",G48*J48,0)) -> 0 | L48: =IF(G48="","",G48+K48) -> 600 | N48: Pending | P48: Source: Harsh fuel list
A49: 45975 | B49: Mauritius Telecom Connect | C49: Fuel | D49: Transport | E49: Harsh | F49: Cash | G49: 600 | H49: Harsh | I49: No | K49: =IF(OR(G49="",I49=""),"",IF(UPPER(I49)="YES",G49*J49,0)) -> 0 | L49: =IF(G49="","",G49+K49) -> 600 | N49: Pending | P49: Source: Harsh fuel list
A50: 45977 | B50: Mauritius Telecom Connect | C50: Fuel | D50: Transport | E50: Harsh | F50: Cash | G50: 600 | H50: Harsh | I50: No | K50: =IF(OR(G50="",I50=""),"",IF(UPPER(I50)="YES",G50*J50,0)) -> 0 | L50: =IF(G50="","",G50+K50) -> 600 | N50: Pending | P50: Source: Harsh fuel list
A51: 45978 | B51: Mauritius Telecom Connect | C51: Fuel | D51: Transport | E51: Harsh | F51: Cash | G51: 600 | H51: Harsh | I51: No | K51: =IF(OR(G51="",I51=""),"",IF(UPPER(I51)="YES",G51*J51,0)) -> 0 | L51: =IF(G51="","",G51+K51) -> 600 | N51: Pending | P51: Source: Harsh fuel list
A52: 45982 | B52: Mauritius Telecom Connect | C52: Fuel | D52: Transport | E52: Harsh | F52: Cash | G52: 600 | H52: Harsh | I52: No | K52: =IF(OR(G52="",I52=""),"",IF(UPPER(I52)="YES",G52*J52,0)) -> 0 | L52: =IF(G52="","",G52+K52) -> 600 | N52: Pending | P52: Source: Harsh fuel list
A53: 45983 | B53: Mauritius Telecom Connect | C53: Fuel | D53: Transport | E53: Harsh | F53: Cash | G53: 600 | H53: Harsh | I53: No | K53: =IF(OR(G53="",I53=""),"",IF(UPPER(I53)="YES",G53*J53,0)) -> 0 | L53: =IF(G53="","",G53+K53) -> 600 | N53: Pending | P53: Source: Harsh fuel list
A54: 45984 | B54: Mauritius Telecom Connect | C54: Fuel | D54: Transport | E54: Harsh | F54: Cash | G54: 600 | H54: Harsh | I54: No | K54: =IF(OR(G54="",I54=""),"",IF(UPPER(I54)="YES",G54*J54,0)) -> 0 | L54: =IF(G54="","",G54+K54) -> 600 | N54: Pending | P54: Source: Harsh fuel list
A55: 45985 | B55: Mauritius Telecom Connect | C55: Fuel | D55: Transport | E55: Harsh | F55: Cash | G55: 600 | H55: Harsh | I55: No | K55: =IF(OR(G55="",I55=""),"",IF(UPPER(I55)="YES",G55*J55,0)) -> 0 | L55: =IF(G55="","",G55+K55) -> 600 | N55: Pending | P55: Source: Harsh fuel list
A56: 45986 | B56: Mauritius Telecom Connect | C56: Fuel | D56: Transport | E56: Harsh | F56: Cash | G56: 600 | H56: Harsh | I56: No | K56: =IF(OR(G56="",I56=""),"",IF(UPPER(I56)="YES",G56*J56,0)) -> 0 | L56: =IF(G56="","",G56+K56) -> 600 | N56: Pending | P56: Source: Harsh fuel list
... A67: 45959 | B67: Mauritius Telecom Connect | C67: Fuel | D67: Transport | E67: Kunal | F67: Cash | G67: 1200 | H67: Kunal | I67: No | K67: =IF(OR(G67="",I67=""),"",IF(UPPER(I67)="YES",G67*J67,0)) -> 0 | L67: =IF(G67="","",G67+K67) -> 1200 | N67: Pending | P67: Source: Kunal list
A68: 45959 | B68: Mauritius Telecom Connect | C68: Food | D68: Food | E68: Kunal | F68: Cash | G68: 1193 | H68: Kunal | I68: Yes | J68: 0.15 | K68: =IF(OR(G68="",I68=""),"",IF(UPPER(I68)="YES",G68*J68,0)) -> 178.95 | L68: =IF(G68="","",G68-K68) -> 1014.05 | N68: Pending | P68: Source: Kunal list
A69: 45969 | B69: Mauritius Telecom Connect | C69: Fuel | D69: Transport | E69: Kunal | F69: Cash | G69: 1200 | H69: Kunal | I69: No | K69: =IF(OR(G69="",I69=""),"",IF(UPPER(I69)="YES",G69*J69,0)) -> 0 | L69: =IF(G69="","",G69+K69) -> 1200 | N69: Pending | P69: Source: Kunal list
A70: 45969 | B70: Mauritius Telecom Connect | C70: Food | D70: Food | E70: Kunal | F70: Cash | G70: 830 | H70: Kunal | I70: Yes | J70: 0.15 | K70: =IF(OR(G70="",I70=""),"",IF(UPPER(I70)="YES",G70*J70,0)) -> 124.5 | L70: =IF(G70="","",G70-K70) -> 705.5 | N70: Pending | P70: Source: Kunal list
A71: 45975 | B71: Mauritius Telecom Connect | C71: Fuel | D71: Transport | E71: Kunal | F71: Cash | G71: 1200 | H71: Kunal | I71: No | K71: =IF(OR(G71="",I71=""),"",IF(UPPER(I71)="YES",G71*J71,0)) -> 0 | L71: =IF(G71="","",G71+K71) -> 1200 | N71: Pending | P71: Source: Kunal list
A72: 45977 | B72: Mauritius Telecom Connect | C72: Fuel | D72: Transport | E72: Kunal | F72: Cash | G72: 1200 | H72: Kunal | I72: No | K72: =IF(OR(G72="",I72=""),"",IF(UPPER(I72)="YES",G72*J72,0)) -> 0 | L72: =IF(G72="","",G72+K72) -> 1200 | N72: Pending | P72: Source: Kunal list
A73: 45978 | B73: Mauritius Telecom Connect | C73: Fuel | D73: Transport | E73: Kunal | F73: Cash | G73: 1200 | H73: Kunal | I73: No | K73: =IF(OR(G73="",I73=""),"",IF(UPPER(I73)="YES",G73*J73,0)) -> 0 | L73: =IF(G73="","",G73+K73) -> 1200 | N73: Pending | P73: Source: Kunal list
A74: 45979 | B74: Mauritius Telecom Connect | C74: Fuel | D74: Transport | E74: Kunal | F74: Cash | G74: 1000 | H74: Kunal | I74: No | K74: =IF(OR(G74="",I74=""),"",IF(UPPER(I74)="YES",G74*J74,0)) -> 0 | L74: =IF(G74="","",G74+K74) -> 1000 | N74: Pending | P74: Source: Kunal list
A75: 45979 | B75: Mauritius Telecom Connect | C75: Food | D75: Food | E75: Kunal | F75: Cash | G75: 2500 | H75: Kunal | I75: Yes | J75: 0.15 | K75: =IF(OR(G75="",I75=""),"",IF(UPPER(I75)="YES",G75*J75,0)) -> 375 | L75: =IF(G75="","",G75-K75) -> 2125 | N75: Pending | P75: Source: Kunal list
A76: 45979 | B76: Mauritius Telecom Connect | C76: Others | D76: Other | E76: Kunal | F76: Cash | G76: 400 | H76: Kunal | I76: No | K76: =IF(OR(G76="",I76=""),"",IF(UPPER(I76)="YES",G76*J76,0)) -> 0 | L76: =IF(G76="","",G76+K76) -> 400 | N76: Pending | P76: Source: Kunal list
A77: 45980 | B77: Mauritius Telecom Connect | C77: Fuel | D77: Transport | E77: Kunal | F77: Cash | G77: 1200 | H77: Kunal | I77: No | K77: =IF(OR(G77="",I77=""),"",IF(UPPER(I77)="YES",G77*J77,0)) -> 0 | L77: =IF(G77="","",G77+K77) -> 1200 | N77: Pending | P77: Source: Kunal list
A78: 45982 | B78: Mauritius Telecom Connect | C78: Fuel | D78: Transport | E78: Kunal | F78: Cash | G78: 1200 | H78: Kunal | I78: No | K78: =IF(OR(G78="",I78=""),"",IF(UPPER(I78)="YES",G78*J78,0)) -> 0 | L78: =IF(G78="","",G78+K78) -> 1200 | N78: Pending | P78: Source: Kunal list
A79: 45983 | B79: Mauritius Telecom Connect | C79: Fuel | D79: Transport | E79: Kunal | F79: Cash | G79: 1200 | H79: Kunal | I79: No | K79: =IF(OR(G79="",I79=""),"",IF(UPPER(I79)="YES",G79*J79,0)) -> 0 | L79: =IF(G79="","",G79+K79) -> 1200 | N79: Pending | P79: Source: Kunal list
A80: 45984 | B80: Mauritius Telecom Connect | C80: Fuel | D80: Transport | E80: Kunal | F80: Cash | G80: 1200 | H80: Kunal | I80: No | K80: =IF(OR(G80="",I80=""),"",IF(UPPER(I80)="YES",G80*J80,0)) -> 0 | L80: =IF(G80="","",G80+K80) -> 1200 | N80: Pending | P80: Source: Kunal list
A81: 45984 | B81: Mauritius Telecom Connect | C81: Others | D81: Other | E81: Kunal | F81: Cash | G81: 440 | H81: Kunal | I81: No | K81: =IF(OR(G81="",I81=""),"",IF(UPPER(I81)="YES",G81*J81,0)) -> 0 | L81: =IF(G81="","",G81+K81) -> 440 | N81: Pending | P81: Source: Kunal list
A82: 45984 | B82: Mauritius Telecom Connect | C82: Cig | D82: Other | E82: Kunal | F82: Cash | G82: 510 | H82: Kunal | I82: No | K82: =IF(OR(G82="",I82=""),"",IF(UPPER(I82)="YES",G82*J82,0)) -> 0 | L82: =IF(G82="","",G82+K82) -> 510 | N82: Pending | P82: Source: Kunal list
A83: 45984 | B83: Mauritius Telecom Connect | C83: Drinks | D83: Food | E83: Kunal | F83: Cash | G83: 350 | H83: Kunal | I83: Yes | J83: 0.15 | K83: =IF(OR(G83="",I83=""),"",IF(UPPER(I83)="YES",G83*J83,0)) -> 52.5 | L83: =IF(G83="","",G83-K83) -> 297.5 | N83: Pending | P83: Source: Kunal list
A84: 45985 | B84: Mauritius Telecom Connect | C84: Others | D84: Other | E84: Kunal | F84: Cash | G84: 3500 | H84: Kunal | I84: No | K84: =IF(OR(G84="",I84=""),"",IF(UPPER(I84)="YES",G84*J84,0)) -> 0 | L84: =IF(G84="","",G84+K84) -> 3500 | N84: Pending | P84: Source: Kunal list
A85: 45985 | B85: Mauritius Telecom Connect | C85: Carnet | D85: Other | E85: Kunal | F85: Cash | G85: 500 | H85: Kunal | I85: No | K85: =IF(OR(G85="",I85=""),"",IF(UPPER(I85)="YES",G85*J85,0)) -> 0 | L85: =IF(G85="","",G85+K85) -> 500 | N85: Pending | P85: Source: Kunal list
A86: 45985 | B86: Mauritius Telecom Connect | C86: Fuel | D86: Transport | E86: Kunal | F86: Cash | G86: 1200 | H86: Kunal | I86: No | K86: =IF(OR(G86="",I86=""),"",IF(UPPER(I86)="YES",G86*J86,0)) -> 0 | L86: =IF(G86="","",G86+K86) -> 1200 | N86: Pending | P86: Source: Kunal list
A87: 45985 | B87: Mauritius Telecom Connect | C87: Others | D87: Other | E87: Kunal | F87: Cash | G87: 440 | H87: Kunal | I87: No | K87: =IF(OR(G87="",I87=""),"",IF(UPPER(I87)="YES",G87*J87,0)) -> 0 | L87: =IF(G87="","",G87+K87) -> 440 | N87: Pending | P87: Source: Kunal list
A88: 45985 | B88: Mauritius Telecom Connect | C88: Groceries | D88: Food | E88: Kunal | F88: Cash | G88: 4793 | H88: Kunal | I88: Yes | J88: 0.15 | K88: =IF(OR(G88="",I88=""),"",IF(UPPER(I88)="YES",G88*J88,0)) -> 718.95 | L88: =IF(G88="","",G88-K88) -> 4074.05 | N88: Pending | P88: Source: Kunal list
A89: 45986 | B89: Mauritius Telecom Connect | C89: Fuel | D89: Transport | E89: Kunal | F89: Cash | G89: 1200 | H89: Kunal | I89: No | K89: =IF(OR(G89="",I89=""),"",IF(UPPER(I89)="YES",G89*J89,0)) -> 0 | L89: =IF(G89="","",G89+K89) -> 1200 | N89: Pending | P89: Source: Kunal list
A90: 45986 | B90: Mauritius Telecom Connect | C90: Others | D90: Other | E90: Kunal | F90: Cash | G90: 220 | H90: Kunal | I90: No | K90: =IF(OR(G90="",I90=""),"",IF(UPPER(I90)="YES",G90*J90,0)) -> 0 | L90: =IF(G90="","",G90+K90) -> 220 | N90: Pending | P90: Source: Kunal list
A91: 45987 | B91: Mauritius Telecom Connect | C91: Fuel | D91: Transport | E91: Kunal | F91: Cash | G91: 1200 | H91: Kunal | I91: No | K91: =IF(OR(G91="",I91=""),"",IF(UPPER(I91)="YES",G91*J91,0)) -> 0 | L91: =IF(G91="","",G91+K91) -> 1200 | N91: Pending | P91: Source: Kunal list
A92: 45988 | B92: Mauritius Telecom Connect | C92: Fuel | D92: Transport | E92: Kunal | F92: Cash | G92: 1000 | H92: Kunal | I92: No | K92: =IF(OR(G92="",I92=""),"",IF(UPPER(I92)="YES",G92*J92,0)) -> 0 | L92: =IF(G92="","",G92+K92) -> 1000 | N92: Pending | P92: Source: Kunal list
A93: 45989 | B93: Mauritius Telecom Connect | C93: Fuel | D93: Transport | E93: Kunal | F93: Cash | G93: 600 | H93: Kunal | I93: No | K93: =IF(OR(G93="",I93=""),"",IF(UPPER(I93)="YES",G93*J93,0)) -> 0 | L93: =IF(G93="","",G93+K93) -> 600 | N93: Pending | P93: Source: Kunal list
A94: 45990 | B94: Mauritius Telecom Connect | C94: Fuel | D94: Transport | E94: Kunal | F94: Cash | G94: 600 | H94: Kunal | I94: No | K94: =IF(OR(G94="",I94=""),"",IF(UPPER(I94)="YES",G94*J94,0)) -> 0 | L94: =IF(G94="","",G94+K94) -> 600 | N94: Pending | P94: Source: Kunal list
A95: 45991 | B95: Mauritius Telecom Connect | C95: Fuel | D95: Transport | E95: Kunal | F95: Cash | G95: 600 | H95: Kunal | I95: No | K95: =IF(OR(G95="",I95=""),"",IF(UPPER(I95)="YES",G95*J95,0)) -> 0 | L95: =IF(G95="","",G95+K95) -> 600 | N95: Pending | P95: Source: Kunal list
A96: 45991 | B96: Mauritius Telecom Connect | C96: Groceries | D96: Food | E96: Kunal | F96: Cash | G96: 2973 | H96: Kunal | I96: Yes | J96: 0.15 | K96: =IF(OR(G96="",I96=""),"",IF(UPPER(I96)="YES",G96*J96,0)) -> 445.95 | L96: =IF(G96="","",G96-K96) -> 2527.05 | N96: Pending | P96: Source: Kunal list
A97: 45992 | B97: Mauritius Telecom Connect | C97: Fuel | D97: Transport | E97: Kunal | F97: Cash | G97: 1200 | H97: Kunal | I97: No | K97: =IF(OR(G97="",I97=""),"",IF(UPPER(I97)="YES",G97*J97,0)) -> 0 | L97: =IF(G97="","",G97+K97) -> 1200 | N97: Pending | P97: Source: Kunal list
A98: 45993 | B98: Mauritius Telecom Connect | C98: Fuel | D98: Transport | E98: Kunal | F98: Cash | G98: 1200 | H98: Kunal | I98: No | K98: =IF(OR(G98="",I98=""),"",IF(UPPER(I98)="YES",G98*J98,0)) -> 0 | L98: =IF(G98="","",G98+K98) -> 1200 | N98: Pending | P98: Source: Kunal list
A99: 45994 | B99: Mauritius Telecom Connect | C99: Fuel | D99: Transport | E99: Kunal | F99: Cash | G99: 1200 | H99: Kunal | I99: No | K99: =IF(OR(G99="",I99=""),"",IF(UPPER(I99)="YES",G99*J99,0)) -> 0 | L99: =IF(G99="","",G99+K99) -> 1200 | N99: Pending | P99: Source: Kunal list
A100: 45995 | B100: Mauritius Telecom Connect | C100: Fuel | D100: Transport | E100: Kunal | F100: Cash | G100: 3000 | H100: Kunal | I100: No | K100: =IF(OR(G100="",I100=""),"",IF(UPPER(I100)="YES",G100*J100,0)) -> 0 | L100: =IF(G100="","",G100+K100) -> 3000 | N100: Pending | P100: Source: Kunal list
A101: 45996 | B101: Mauritius Telecom Connect | C101: Fuel | D101: Transport | E101: Kunal | F101: Cash | G101: 1200 | H101: Kunal | I101: No | K101: =IF(OR(G101="",I101=""),"",IF(UPPER(I101)="YES",G101*J101,0)) -> 0 | L101: =IF(G101="","",G101+K101) -> 1200 | N101: Pending | P101: Source: Kunal list
A102: 45980 | B102: Mauritius Telecom Connect | C102: Food | D102: Food | E102: Avneesh | F102: Cash | G102: 462.8 | H102: Avneesh | I102: Yes | J102: 0.15 | K102: =IF(OR(G102="",I102=""),"",IF(UPPER(I102)="YES",G102*J102,0)) -> 69.42 | L102: =IF(G102="","",G102-K102) -> 393.38 | N102: Pending | P102: Source: Avneesh list
A103: 45980 | B103: Mauritius Telecom Connect | C103: Food | D103: Food | E103: Avneesh | F103: Cash | G103: 550 | H103: Avneesh | I103: Yes | J103: 0.15 | K103: =IF(OR(G103="",I103=""),"",IF(UPPER(I103)="YES",G103*J103,0)) -> 82.5 | L103: =IF(G103="","",G103-K103) -> 467.5 | N103: Pending | P103: Source: Avneesh list
A104: 45980 | B104: Mauritius Telecom Connect | C104: Food | D104: Food | E104: Avneesh | F104: Cash | G104: 487 | H104: Avneesh | I104: Yes | J104: 0.15 | K104: =IF(OR(G104="",I104=""),"",IF(UPPER(I104)="YES",G104*J104,0)) -> 73.05 | L104: =IF(G104="","",G104-K104) -> 413.95 | N104: Pending | P104: Source: Avneesh list
A105: 45980 | B105: Mauritius Telecom Connect | C105: Food | D105: Food | E105: Avneesh | F105: Cash | G105: 680 | H105: Avneesh | I105: Yes | J105: 0.15 | K105: =IF(OR(G105="",I105=""),"",IF(UPPER(I105)="YES",G105*J105,0)) -> 102 | L105: =IF(G105="","",G105-K105) -> 578 | N105: Pending | P105: Source: Avneesh list
A106: 45980 | B106: Mauritius Telecom Connect | C106: Food | D106: Food | E106: Avneesh | F106: Cash | G106: 90 | H106: Avneesh | I106: Yes | J106: 0.15 | K106: =IF(OR(G106="",I106=""),"",IF(UPPER(I106)="YES",G106*J106,0)) -> 13.5 | L106: =IF(G106="","",G106-K106) -> 76.5 | N106: Pending | P106: Source: Avneesh list
A107: 45980 | B107: Mauritius Telecom Connect | C107: Food | D107: Food | E107: Avneesh | F107: Cash | G107: 265 | H107: Avneesh | I107: Yes | J107: 0.15 | K107: =IF(OR(G107="",I107=""),"",IF(UPPER(I107)="YES",G107*J107,0)) -> 39.75 | L107: =IF(G107="","",G107-K107) -> 225.25 | N107: Pending | P107: Source: Avneesh list
A108: 45980 | B108: Mauritius Telecom Connect | C108: Food | D108: Food | E108: Avneesh | F108: Cash | G108: 975.75 | H108: Avneesh | I108: Yes | J108: 0.15 | K108: =IF(OR(G108="",I108=""),"",IF(UPPER(I108)="YES",G108*J108,0)) -> 146.3625 | L108: =IF(G108="","",G108-K108) -> 829.3875 | N108: Pending | P108: Source: Avneesh list
A109: 45980 | B109: Mauritius Telecom Connect | C109: Food | D109: Food | E109: Avneesh | F109: Cash | G109: 2700 | H109: Avneesh | I109: Yes | J109: 0.15 | K109: =IF(OR(G109="",I109=""),"",IF(UPPER(I109)="YES",G109*J109,0)) -> 405 | L109: =IF(G109="","",G109-K109) -> 2295 | N109: Pending | P109: Source: Avneesh list
A110: 45983 | B110: Mauritius Telecom Connect | C110: Food | D110: Food | E110: Avneesh | F110: Cash | G110: 1107 | H110: Avneesh | I110: Yes | J110: 0.15 | K110: =IF(OR(G110="",I110=""),"",IF(UPPER(I110)="YES",G110*J110,0)) -> 166.05 | L110: =IF(G110="","",G110-K110) -> 940.95 | N110: Pending | P110: Source: Avneesh list
...

Sheet Cash
A1: Date | B1: Project | C1: Person | D1: Description | E1: Category | F1: Amount (Rs) | G1: Type | H1: Status | I1: Reimbursed Date | J1: Linked Expense Ref | K1: Notes
B2: Mauritius Telecom Connect | C2: Harsh | D2: Fuel / Food / Misc | E2: Food | F2: 7800 | G2: Advance | H2: Owed
B3: Mauritius Telecom Connect | C3: Avneesh | D3: Food / Misc | E3: Food | F3: 8817.55 | G3: Advance | H3: Owed
B4: Mauritius Telecom Connect | C4: Williams | D4: Food / Misc | E4: Food | F4: 200 | G4: Advance | H4: Owed

Sheet Dashboard
A1: PROJECT FINANCIAL DASHBOARD (MUR)
A3: Project: | B3: Mauritius Telecom Connect | C3: Month (YYYY-MM):
A4: FINAL BREAKDOWN — Income vs Expenses, Who Paid What
A6: Total Income (Approved Quote) | B6: =Approved_KRIS!B29 -> 1600500 | F6: DISCOUNT (Kris) | G6: =Approved_KRIS!B26 -> 80000
A7: Total Expenses (Excl VAT) | B7: =E17+E35 -> 1030841.3 | E7: Amount (Rs) | F7: Agency Fee (10%) | G7: =Approved_KRIS!B28 -> 145500
A8: VAT on Expenses | B8: =IF($B$3="","",SUMIFS(tblExpenses[VAT Amount (Rs)],tblExpenses[Project],$B$3)) -> 9249.4935 | E8: =IF($B$3="","",IF(SUMIFS(tblExpenses[Total excl VAT (Rs)],tblExpenses[Project],$B$3,tblExpenses[Paid By],$D8)=0,"",SUMIFS(tblExpenses[Total excl VAT (Rs)],tblExpenses[Project],$B$3,tblExpenses[Paid By],$D8))) | F8: Income excl VAT | G8: =Approved_KRIS!B29 -> 1600500
A9: Total Expenses (Incl VAT) | B9: =B7*15% -> 154626.2 | D9: Avneesh | E9: =IF($B$3="","",IF(SUMIFS(tblExpenses[Total excl VAT (Rs)],tblExpenses[Project],$B$3,tblExpenses[Paid By],$D9)=0,"",SUMIFS(tblExpenses[Total excl VAT (Rs)],tblExpenses[Project],$B$3,tblExpenses[Paid By],$D9))) -> 7494.9175 | F9: VAT on Total Income | G9: =Approved_KRIS!B30 -> 240075
A10: Net Result (Income - Expenses incl VAT) | B10: =IF(OR(B6="",B9=""),"",B6-B9) -> 1445873.8 | D10: Long | E10: =IF($B$3="","",IF(SUMIFS(tblExpenses[Total excl VAT (Rs)],tblExpenses[Project],$B$3,tblExpenses[Paid By],$D10)=0,"",SUMIFS(tblExpenses[Total excl VAT (Rs)],tblExpenses[Project],$B$3,tblExpenses[Paid By],$D10))) | F10: Income incl VAT | G10: =Approved_KRIS!B31 -> 1840575
A11: Gross Margin % | B11: =IF(B6="","",IF(B6=0,"",B10/B6)) -> 0.90338882 | D11: Williams | E11: =IF($B$3="","",IF(SUMIFS(tblExpenses[Total excl VAT (Rs)],tblExpenses[Project],$B$3,tblExpenses[Paid By],$D11)=0,"",SUMIFS(tblExpenses[Total excl VAT (Rs)],tblExpenses[Project],$B$3,tblExpenses[Paid By],$D11)))
A12: Total Cash Owed (Advances not reimbursed) | B12: =IF($B$3="","",SUMIFS(tblCash[Amount (Rs)],tblCash[Project],$B$3,tblCash[Status],"Owed")) -> 16817.55 | D12: Laura | E12: =IF($B$3="","",IF(SUMIFS(tblExpenses[Total excl VAT (Rs)],tblExpenses[Project],$B$3,tblExpenses[Paid By],$D12)=0,"",SUMIFS(tblExpenses[Total excl VAT (Rs)],tblExpenses[Project],$B$3,tblExpenses[Paid By],$D12)))
A13: Description | B13: Paid By | C13: Total (Rs) | D13: Other | E13: =IF($B$3="","",IF(SUMIFS(tblExpenses[Total excl VAT (Rs)],tblExpenses[Project],$B$3,tblExpenses[Paid By],$D13)=0,"",SUMIFS(tblExpenses[Total excl VAT (Rs)],tblExpenses[Project],$B$3,tblExpenses[Paid By],$D13)))
A14: (Tip) For detailed top-lines, sort the Expenses table by Total Incl VAT. | D14: Harsh | E14: =IF($B$3="","",IF(SUMIFS(tblExpenses[Total excl VAT (Rs)],tblExpenses[Project],$B$3,tblExpenses[Paid By],$D14)=0,"",SUMIFS(tblExpenses[Total excl VAT (Rs)],tblExpenses[Project],$B$3,tblExpenses[Paid By],$D14))) -> 12000
D15: Kunal | E15: =IF($B$3="","",IF(SUMIFS(tblExpenses[Total excl VAT (Rs)],tblExpenses[Project],$B$3,tblExpenses[Paid By],$D15)=0,"",SUMIFS(tblExpenses[Total excl VAT (Rs)],tblExpenses[Project],$B$3,tblExpenses[Paid By],$D15))) -> 42753.15
A16: INCOME BY CATEGORY | D16: Petty Cash | E16: =IF($B$3="","",IF(SUMIFS(tblExpenses[Total excl VAT (Rs)],tblExpenses[Project],$B$3,tblExpenses[Paid By],$D16)=0,"",SUMIFS(tblExpenses[Total excl VAT (Rs)],tblExpenses[Project],$B$3,tblExpenses[Paid By],$D16))) -> 53352.439
A17: Category | B17: Amount (Rs) | D17: TOTAL | E17: =SUM(E9:E16) -> 115600.51
A18: Creative Direction | B18: =IF($B$3="","",IF(SUMIFS(tblRevenue[Line Total (Rs)],tblRevenue[Project],$B$3,tblRevenue[Category],$A18)=0,"",SUMIFS(tblRevenue[Line Total (Rs)],tblRevenue[Project],$B$3,tblRevenue[Category],$A18))) -> 300000
A19: Design | B19: =IF($B$3="","",IF(SUMIFS(tblRevenue[Line Total (Rs)],tblRevenue[Project],$B$3,tblRevenue[Category],$A19)=0,"",SUMIFS(tblRevenue[Line Total (Rs)],tblRevenue[Project],$B$3,tblRevenue[Category],$A19))) -> 525000 | D19: EXPENSES BY CATEGORY | E19: =IF($B$3="","",IF(SUMIFS(tblExpenses[Total excl VAT (Rs)],tblExpenses[Project],$B$3,tblExpenses[Paid By],$D19)=0,"",SUMIFS(tblExpenses[Total excl VAT (Rs)],tblExpenses[Project],$B$3,tblExpenses[Paid By],$D19)))
A20: Video | B20: =IF($B$3="","",IF(SUMIFS(tblRevenue[Line Total (Rs)],tblRevenue[Project],$B$3,tblRevenue[Category],$A20)=0,"",SUMIFS(tblRevenue[Line Total (Rs)],tblRevenue[Project],$B$3,tblRevenue[Category],$A20))) -> 320000 | D20: Category | E20: =IF($B$3="","",IF(SUMIFS(tblExpenses[Total excl VAT (Rs)],tblExpenses[Project],$B$3,tblExpenses[Paid By],$D20)=0,"",SUMIFS(tblExpenses[Total excl VAT (Rs)],tblExpenses[Project],$B$3,tblExpenses[Paid By],$D20)))
A21: Tech/AV | B21: =IF($B$3="","",IF(SUMIFS(tblRevenue[Line Total (Rs)],tblRevenue[Project],$B$3,tblRevenue[Category],$A21)=0,"",SUMIFS(tblRevenue[Line Total (Rs)],tblRevenue[Project],$B$3,tblRevenue[Category],$A21))) -> 70000 | D21: Creative Direction | E21: =IF($B$3="","",IF(SUMIFS(tblExpenses[Total excl VAT (Rs)],tblExpenses[Project],$B$3,tblExpenses[Category],$D21)=0,"",SUMIFS(tblExpenses[Total excl VAT (Rs)],tblExpenses[Project],$B$3,tblExpenses[Category],$D21))) -> 349000
A22: Scenography | B22: =IF($B$3="","",IF(SUMIFS(tblRevenue[Line Total (Rs)],tblRevenue[Project],$B$3,tblRevenue[Category],$A22)=0,"",SUMIFS(tblRevenue[Line Total (Rs)],tblRevenue[Project],$B$3,tblRevenue[Category],$A22))) | D22: Design | E22: =IF($B$3="","",IF(SUMIFS(tblExpenses[Total excl VAT (Rs)],tblExpenses[Project],$B$3,tblExpenses[Category],$D22)=0,"",SUMIFS(tblExpenses[Total excl VAT (Rs)],tblExpenses[Project],$B$3,tblExpenses[Category],$D22))) -> 120000
A23: Production | B23: 130000 | D23: Video | E23: =IF($B$3="","",IF(SUMIFS(tblExpenses[Total excl VAT (Rs)],tblExpenses[Project],$B$3,tblExpenses[Category],$D23)=0,"",SUMIFS(tblExpenses[Total excl VAT (Rs)],tblExpenses[Project],$B$3,tblExpenses[Category],$D23))) -> 285000
A24: Travel | B24: =IF($B$3="","",IF(SUMIFS(tblRevenue[Line Total (Rs)],tblRevenue[Project],$B$3,tblRevenue[Category],$A24)=0,"",SUMIFS(tblRevenue[Line Total (Rs)],tblRevenue[Project],$B$3,tblRevenue[Category],$A24))) | D24: Tech/AV | E24: =IF($B$3="","",IF(SUMIFS(tblExpenses[Total excl VAT (Rs)],tblExpenses[Project],$B$3,tblExpenses[Category],$D24)=0,"",SUMIFS(tblExpenses[Total excl VAT (Rs)],tblExpenses[Project],$B$3,tblExpenses[Category],$D24))) -> 810
A25: Food | B25: =IF($B$3="","",IF(SUMIFS(tblRevenue[Line Total (Rs)],tblRevenue[Project],$B$3,tblRevenue[Category],$A25)=0,"",SUMIFS(tblRevenue[Line Total (Rs)],tblRevenue[Project],$B$3,tblRevenue[Category],$A25))) -> 120000 | D25: Scenography | E25: =IF($B$3="","",IF(SUMIFS(tblExpenses[Total excl VAT (Rs)],tblExpenses[Project],$B$3,tblExpenses[Category],$D25)=0,"",SUMIFS(tblExpenses[Total excl VAT (Rs)],tblExpenses[Project],$B$3,tblExpenses[Category],$D25)))
A26: TOTAL | B26: =SUM(B18:B25) -> 1465000 | D26: Production | E26: =IF($B$3="","",IF(SUMIFS(tblExpenses[Total excl VAT (Rs)],tblExpenses[Project],$B$3,tblExpenses[Category],$D26)=0,"",SUMIFS(tblExpenses[Total excl VAT (Rs)],tblExpenses[Project],$B$3,tblExpenses[Category],$D26))) -> 70000
D27: Travel | E27: =IF($B$3="","",IF(SUMIFS(tblExpenses[Total excl VAT (Rs)],tblExpenses[Project],$B$3,tblExpenses[Category],$D27)=0,"",SUMIFS(tblExpenses[Total excl VAT (Rs)],tblExpenses[Project],$B$3,tblExpenses[Category],$D27)))
D28: Food | E28: =IF($B$3="","",IF(SUMIFS(tblExpenses[Total excl VAT (Rs)],tblExpenses[Project],$B$3,tblExpenses[Category],$D28)=0,"",SUMIFS(tblExpenses[Total excl VAT (Rs)],tblExpenses[Project],$B$3,tblExpenses[Category],$D28))) -> 52413.797
D29: Transport | E29: =IF($B$3="","",IF(SUMIFS(tblExpenses[Total excl VAT (Rs)],tblExpenses[Project],$B$3,tblExpenses[Category],$D29)=0,"",SUMIFS(tblExpenses[Total excl VAT (Rs)],tblExpenses[Project],$B$3,tblExpenses[Category],$D29))) -> 38000
D30: Accommodation | E30: =IF($B$3="","",IF(SUMIFS(tblExpenses[Total excl VAT (Rs)],tblExpenses[Project],$B$3,tblExpenses[Category],$D30)=0,"",SUMIFS(tblExpenses[Total excl VAT (Rs)],tblExpenses[Project],$B$3,tblExpenses[Category],$D30)))
D31: Printing | E31: =IF($B$3="","",IF(SUMIFS(tblExpenses[Total excl VAT (Rs)],tblExpenses[Project],$B$3,tblExpenses[Category],$D31)=0,"",SUMIFS(tblExpenses[Total excl VAT (Rs)],tblExpenses[Project],$B$3,tblExpenses[Category],$D31)))
D32: Rentals | E32: =IF($B$3="","",IF(SUMIFS(tblExpenses[Total excl VAT (Rs)],tblExpenses[Project],$B$3,tblExpenses[Category],$D32)=0,"",SUMIFS(tblExpenses[Total excl VAT (Rs)],tblExpenses[Project],$B$3,tblExpenses[Category],$D32)))
D33: Discount
D34: Subotal | E34: =SUM(E21:E33) -> 915223.8
A35: If any totals show blank, check the Project name matches exactly in Revenue/Expenses/Cash tables. | B35: =IF($B$3="","",IF(SUMIFS(tblRevenue[Line Total (Rs)],tblRevenue[Project],$B$3,tblRevenue[Category],$A35)=0,"",SUMIFS(tblRevenue[Line Total (Rs)],tblRevenue[Project],$B$3,tblRevenue[Category],$A35))) | D35: TOTAL | E35: =17+E34 -> 915240.8
A40: How to use:
A41: 1) Fill Revenue / Expenses / Cash tables. 2) Type the project name in Dashboard!B3 to see totals.
A44: Expenses by Paid By
A45: Paid By | B45: Amount (Rs)
A46: ë | B46: =IF($B$3="","",SUMIFS(tblExpenses[Total excl VAT (Rs)],tblExpenses[Project],$B$3,tblExpenses[Paid By],$A46)) -> 873500
A47: Avneesh | B47: =IF($B$3="","",SUMIFS(tblExpenses[Total excl VAT (Rs)],tblExpenses[Project],$B$3,tblExpenses[Paid By],$A47)) -> 7494.9175
A48: Long | B48: =IF($B$3="","",SUMIFS(tblExpenses[Total excl VAT (Rs)],tblExpenses[Project],$B$3,tblExpenses[Paid By],$A48)) -> 0
A49: Williams | B49: =IF($B$3="","",SUMIFS(tblExpenses[Total excl VAT (Rs)],tblExpenses[Project],$B$3,tblExpenses[Paid By],$A49)) -> 0
A50: Laura | B50: =IF($B$3="","",SUMIFS(tblExpenses[Total excl VAT (Rs)],tblExpenses[Project],$B$3,tblExpenses[Paid By],$A50)) -> 0
A51: Other | B51: =IF($B$3="","",SUMIFS(tblExpenses[Total excl VAT (Rs)],tblExpenses[Project],$B$3,tblExpenses[Paid By],$A51)) -> 0
A52: Harsh | B52: =IF($B$3="","",SUMIFS(tblExpenses[Total excl VAT (Rs)],tblExpenses[Project],$B$3,tblExpenses[Paid By],$A52)) -> 12000
A53: Kunal | B53: =IF($B$3="","",SUMIFS(tblExpenses[Total excl VAT (Rs)],tblExpenses[Project],$B$3,tblExpenses[Paid By],$A53)) -> 42753.15
A54: Petty Cash | B54: =IF($B$3="","",SUMIFS(tblExpenses[Total excl VAT (Rs)],tblExpenses[Project],$B$3,tblExpenses[Paid By],$A54)) -> 53352.439
A57: Tip: Fill Dashboard!B3 with the project name to refresh the resume (e.g. Mauritius Telecom Connect).
